smart_assertions/__init__.py
smart_assertions/smart_assertions.py
smart_assertions-1.0.2.dist-info/LICENSE
smart_assertions-1.0.2.dist-info/METADATA
smart_assertions-1.0.2.dist-info/WHEEL
smart_assertions-1.0.2.dist-info/top_level.txt
smart_assertions-1.0.2.dist-info/RECORD
