Metadata-Version: 2.1
Name: smart-assertions
Version: 1.0.2
Summary: Soft assertions for Python
Home-page: https://github.com/balalaiQA/smart-assertions
Author: balalaiQA
License: UNKNOWN
Platform: UNKNOWN
